superluminal/__init__.py
superluminal-1.0.0a6.dist-info/METADATA
superluminal-1.0.0a6.dist-info/WHEEL
superluminal-1.0.0a6.dist-info/top_level.txt
superluminal-1.0.0a6.dist-info/RECORD
